docs/conf.py
examples/publisher.py
examples/subscriber.py
pigeon/__init__.py
pigeon/__main__.py
pigeon/client.py
pigeon/exceptions.py
pigeon/messages.py
pigeon/utils.py
pigeon_client-3.0.2.dist-info/licenses/LICENSE
tests/test_base_message.py
tests/test_client.py
tests/test_message_handler.py
tests/test_utils.py
pigeon_client-3.0.2.dist-info/METADATA
pigeon_client-3.0.2.dist-info/WHEEL
pigeon_client-3.0.2.dist-info/entry_points.txt
pigeon_client-3.0.2.dist-info/top_level.txt
pigeon_client-3.0.2.dist-info/RECORD
