Metadata-Version: 2.4
Name: pigeon-client
Version: 3.0.2
Summary: A STOMP client with message definitions via Pydantic
Author-email: Cameron Devine <cameron.devine@alleninstitute.org>
License-Expression: BSD-3-Clause
Project-URL: Homepage, https://github.com/AllenInstitute/pigeon
Project-URL: Documentation, http://pigeon.readthedocs.io/
Project-URL: Repository, https://github.com/AllenInstitute/pigeon
Project-URL: Issues, https://github.com/AllenInstitute/pigeon/issues
Classifier: Intended Audience :: Developers
Classifier: Programming Language :: Python :: 3.10
Classifier: Programming Language :: Python :: 3.11
Classifier: Programming Language :: Python :: 3.12
Requires-Python: >=3.10
License-File: LICENSE
Requires-Dist: pydantic
Requires-Dist: stomp-py
Requires-Dist: pyyaml
Requires-Dist: python-logging-loki
Requires-Dist: jsonschema2md
Requires-Dist: rich
Provides-Extra: test
Requires-Dist: pytest; extra == "test"
Requires-Dist: pytest-mock; extra == "test"
Requires-Dist: pytest-timeout; extra == "test"
Dynamic: license-file
